starlight_vision/__init__.py
starlight_vision/core/__init__.py
starlight_vision/core/attention.py
starlight_vision/core/elucidated.py
starlight_vision/core/gen2.py
starlight_vision/core/gen2_video.py
starlight_vision/core/starlight.py
starlight_vision/core/starlightv2.py
starlight_vision/core/t5.py
starlight_vision/model.py
starlight_vision/trainer.py
starlight_vision-0.1.1.dist-info/LICENSE
starlight_vision-0.1.1.dist-info/WHEEL
starlight_vision-0.1.1.dist-info/METADATA
starlight_vision-0.1.1.dist-info/RECORD
