Metadata-Version: 2.1
Name: starlight-vision
Version: 0.1.1
Summary: Starlight - unprecedented photorealism × deep level of language understanding
Home-page: https://github.com/kyegomez/StarlightVision
License: MIT
Keywords: artificial intelligence,deep learning,transformers,text-to-image,denoising-diffusion
Author: Kye Gomez
Author-email: kye@apac.ai
Requires-Python: >=3.6,<4.0
Classifier: Development Status :: 4 - Beta
Classifier: Intended Audience :: Developers
Classifier: License :: OSI Approved :: MIT License
Classifier: Programming Language :: Python :: 3
Classifier: Programming Language :: Python :: 3.6
Classifier: Programming Language :: Python :: 3.7
Classifier: Programming Language :: Python :: 3.8
Classifier: Programming Language :: Python :: 3.9
Classifier: Programming Language :: Python :: 3.10
Classifier: Programming Language :: Python :: 3.11
Classifier: Programming Language :: Python :: 3.6
Classifier: Topic :: Scientific/Engineering :: Artificial Intelligence
Requires-Dist: accelerate
Requires-Dist: beartype
Requires-Dist: click
Requires-Dist: datasets
Requires-Dist: einops (>=0.6.1)
Requires-Dist: ema-pytorch (>=0.0.3)
Requires-Dist: fsspec
Requires-Dist: kornia
Requires-Dist: lion-pytorch
Requires-Dist: numpy
Requires-Dist: packaging
Requires-Dist: pillow
Requires-Dist: pydantic (>=2)
Requires-Dist: pytorch-lightning
Requires-Dist: pytorch-warmup
Requires-Dist: sentencepiece
Requires-Dist: torch (>=1.6)
Requires-Dist: torchvision
Requires-Dist: tqdm
Requires-Dist: transformers
Requires-Dist: triton
